LICENSE
MANIFEST.in
README.md
requirements.txt
setup.py
bert4vector/__init__.py
bert4vector.egg-info/PKG-INFO
bert4vector.egg-info/SOURCES.txt
bert4vector.egg-info/dependency_links.txt
bert4vector.egg-info/requires.txt
bert4vector.egg-info/top_level.txt
bert4vector/config/cilin.txt
bert4vector/config/hownet.txt
bert4vector/config/stopwords.txt
bert4vector/core/__init__.py
bert4vector/core/base.py
bert4vector/core/bert.py
bert4vector/core/faiss.py
bert4vector/core/lteral.py
bert4vector/core/openai.py
bert4vector/pipelines/__init__.py
bert4vector/pipelines/api.py
bert4vector/snippets/__init__.py
bert4vector/snippets/distance.py
bert4vector/snippets/rank_bm25.py
bert4vector/snippets/tfidf.py
bert4vector/snippets/util_numpy.py
bert4vector/snippets/util_torch.py
test/test_bert_similarity.py
test/test_faiss_similarity.py
test/test_lteral_similarity.py