Metadata-Version: 2.1
Name: bert4vector
Version: 0.0.7.post2
Summary: an elegant bert4vector
Home-page: https://github.com/Tongjilibo/bert4vector
Author: Tongjilibo
Author-email: tongjilibo@163.com
License: MIT Licence
License-File: LICENSE
Requires-Dist: numpy
Requires-Dist: loguru
Requires-Dist: torch4keras
Provides-Extra: bert4torch
Requires-Dist: bert4torch; extra == "bert4torch"
Provides-Extra: transformers
Requires-Dist: transformers; extra == "transformers"
Provides-Extra: sentence-transformers
Requires-Dist: sentence_transformers; extra == "sentence-transformers"
